Workbook

Sheet Loan_Applications_Raw
A1: Application_ID | B1: Applicant_Age | C1: Annual_Income | D1: Employment_Status | E1: Employment_Length_Yrs | F1: Credit_Score | G1: Existing_Debt | H1: Monthly_Debt_Payment | I1: Loan_Amount | J1: Loan_Term_Months | K1: Loan_Purpose | L1: Past_Defaults | M1: Delinquencies_12M | N1: Bankruptcy_Flag
A2: APP-001 | B2: 28 | C2: 52000 | D2: Salaried | E2: 3 | F2: 720 | G2: 18000 | H2: 450 | I2: 15000 | J2: 36 | K2: Auto | L2: 0 | M2: 1 | N2: No
A3: APP-002 | B3: 34 | C3: 68000 | D3: Salaried | E3: 6 | F3: 680 | G3: 25000 | H3: 620 | I3: 20000 | J3: 60 | K3: Personal | L3: 0 | M3: 2 | N3: No
A4: APP-003 | B4: 45 | C4: 95000 | D4: Salaried | E4: 15 | F4: 760 | G4: 30000 | H4: 700 | I4: 25000 | J4: 36 | K4: Consolidation | L4: 0 | M4: 0 | N4: No
A5: APP-004 | B5: 52 | C5: 120000 | D5: Self-Employed | E5: 20 | F5: 810 | G5: 20000 | H5: 520 | I5: 30000 | J5: 60 | K5: Auto | L5: 1 | M5: 3 | N5: No
A6: APP-005 | B6: 31 | C6: 60000 | D6: Salaried | E6: 5 | F6: 650 | G6: 22000 | H6: 580 | I6: 18000 | J6: 36 | K6: Personal | L6: 0 | M6: 1 | N6: No
A7: APP-006 | B7: 40 | C7: 85000 | D7: Salaried | E7: 10 | F7: 700 | G7: 28000 | H7: 650 | I7: 22000 | J7: 60 | K7: Consolidation | L7: 0 | M7: 2 | N7: No
A8: APP-007 | B8: 27 | C8: 48000 | D8: Contract | E8: 2 | F8: 610 | G8: 15000 | H8: 400 | I8: 12000 | J8: 36 | K8: Personal | L8: 1 | M8: 4 | N8: No
A9: APP-008 | B9: 36 | C9: 72000 | D9: Salaried | E9: 7 | F9: 690 | G9: 26000 | H9: 610 | I9: 20000 | J9: 60 | K9: Auto | L9: 0 | M9: 1 | N9: No
A10: APP-009 | B10: 60 | C10: 140000 | D10: Salaried | E10: 25 | F10: 790 | G10: 35000 | H10: 800 | I10: 35000 | J10: 60 | K10: Consolidation | L10: 0 | M10: 0 | N10: No
A11: APP-010 | B11: 49 | C11: 98000 | D11: Self-Employed | E11: 18 | F11: 670 | G11: 24000 | H11: 590 | I11: 24000 | J11: 36 | K11: Personal | L11: 1 | M11: 2 | N11: No
A12: APP-011 | B12: 33 | C12: 65000 | D12: Salaried | E12: 4 | F12: 640 | G12: 21000 | H12: 540 | I12: 17000 | J12: 36 | K12: Auto | L12: 0 | M12: 1 | N12: No
A13: APP-012 | B13: 55 | C13: 110000 | D13: Self-Employed | E13: 22 | F13: 750 | G13: 27000 | H13: 670 | I13: 28000 | J13: 60 | K13: Consolidation | L13: 0 | M13: 0 | N13: No
... A21: APP-020 | B21: 44 | C21: 92000 | D21: Salaried | E21: 16 | F21: 740 | G21: 30000 | H21: 710 | I21: 27000 | J21: 60 | K21: Personal | L21: 0 | M21: 0 | N21: No

Sheet Cleaned_Data
A1: Application_ID | B1: Applicant_Age | C1: Employment_Status | D1: Employment_Length_Yrs | E1: Annual_Income | F1: Existing_Debt | G1: Monthly_Debt_Payment | H1: Loan_Amount | I1: Loan_Term_Months | J1: Loan_Purpose | K1: Credit_Score | L1: Credit_Score_Band | M1: Past_Defaults | N1: Delinquencies_12M | O1: Bankruptcy_Flag | P1: Monthly_Income | Q1: Debt_to_Income | R1: Loan_to_Income | S1: Risk_Flags_Count | T1: Score_Credit | U1: Score_DTI | V1: Score_Employment | W1: Score_Past_Defaults | X1: Score_Delinquencies | Y1: Risk_Score | Z1: Risk_Tier | AA1: Policy_Override | AB1: Lending_Decision | AD1: Portfolio Risk Summary
A2: APP-001 | B2: 28 | C2: Salaried | D2: 3 | E2: 52000 | F2: 18000 | G2: 580 | H2: 15000 | I2: 36 | J2: Auto | K2: 720 | L2: =IF(K2>=750,"Prime",IF(K2>=700,"Near-Prime","Subprime")) -> Near-Prime | M2: 0 | N2: 1 | O2: No | P2: =E2/12 -> 4333.3333 | Q2: =G2/P2 -> 0.13384615 | R2: =H2/E2 -> 0.28846154 | S2: =(M2>0)+(N2>=3)+(O2="Yes")+(Q2>0.4) -> 0 | T2: =IF(K2>=750,100, IF(K2>=700,85, IF(K2>=650,70, IF(K2>=600,50,30)))) -> 85 | U2: =IF(Q2<=0.25,100, IF(Q2<=0.35,80, IF(Q2<=0.5,60,30))) -> 100 | V2: =IF(D2>=10,100, IF(D2>=5,80, IF(D2>=2,60,30))) -> 60 | W2: =IF(M2=0,100,IF(M2=1,50,20)) -> 100 | X2: =IF(N2=0,100,IF(N2<=2,70,30)) -> 70 | Y2: =T2*0.35 + U2*0.25 + V2*0.15 + W2*0.15 + X2*0.1 -> 85.75 | Z2: =IF(Y2>=80,"Low Risk", IF(Y2>=65,"Medium Risk", IF(Y2>=50,"High Risk","Very High Risk"))) -> Low Risk | AA2: =IF(O2="Yes","Auto Decline", IF(M2>=2,"Auto Decline", IF(Q2>0.45,"High DTI Review", IF(S2>=2,"Enhanced Review","None")))) -> None | AB2: =IF(AA2="Auto Decline","Decline", IF(AA2="High DTI Review","Manual Review", IF(AA2="Enhanced Review","Manual Review", IF(Z2="Low Risk","Approve", IF(Z2="Medium Risk","Manual Review", IF(Z2="High Risk","Conditional Review","Decline")))))) -> Approve
A3: APP-002 | B3: 34 | C3: Salaried | D3: 6 | E3: 68000 | F3: 25000 | G3: 620 | H3: 20000 | I3: 60 | J3: Personal | K3: 680 | L3: =IF(K3>=750,"Prime",IF(K3>=700,"Near-Prime","Subprime")) -> Subprime | M3: 0 | N3: 2 | O3: No | P3: =E3/12 -> 5666.6667 | Q3: =G3/P3 -> 0.10941176 | R3: =H3/E3 -> 0.29411765 | S3: =(M3>0)+(N3>=3)+(O3="Yes")+(Q3>0.4) -> 0 | T3: =IF(K3>=750,100, IF(K3>=700,85, IF(K3>=650,70, IF(K3>=600,50,30)))) -> 70 | U3: =IF(Q3<=0.25,100, IF(Q3<=0.35,80, IF(Q3<=0.5,60,30))) -> 100 | V3: =IF(D3>=10,100, IF(D3>=5,80, IF(D3>=2,60,30))) -> 80 | W3: =IF(M3=0,100,IF(M3=1,50,20)) -> 100 | X3: =IF(N3=0,100,IF(N3<=2,70,30)) -> 70 | Y3: =T3*0.35 + U3*0.25 + V3*0.15 + W3*0.15 + X3*0.1 -> 83.5 | Z3: =IF(Y3>=80,"Low Risk", IF(Y3>=65,"Medium Risk", IF(Y3>=50,"High Risk","Very High Risk"))) -> Low Risk | AA3: =IF(O3="Yes","Auto Decline", IF(M3>=2,"Auto Decline", IF(Q3>0.45,"High DTI Review", IF(S3>=2,"Enhanced Review","None")))) -> None | AB3: =IF(AA3="Auto Decline","Decline", IF(AA3="High DTI Review","Manual Review", IF(AA3="Enhanced Review","Manual Review", IF(Z3="Low Risk","Approve", IF(Z3="Medium Risk","Manual Review", IF(Z3="High Risk","Conditional Review","Decline")))))) -> Approve | AD3: Total Applications | AE3: =COUNTA(A2:A21) -> 20
A4: APP-003 | B4: 45 | C4: Salaried | D4: 15 | E4: 95000 | F4: 30000 | G4: 700 | H4: 25000 | I4: 36 | J4: Consolidation | K4: 760 | L4: =IF(K4>=750,"Prime",IF(K4>=700,"Near-Prime","Subprime")) -> Prime | M4: 0 | N4: 0 | O4: No | P4: =E4/12 -> 7916.6667 | Q4: =G4/P4 -> 0.088421053 | R4: =H4/E4 -> 0.26315789 | S4: =(M4>0)+(N4>=3)+(O4="Yes")+(Q4>0.4) -> 0 | T4: =IF(K4>=750,100, IF(K4>=700,85, IF(K4>=650,70, IF(K4>=600,50,30)))) -> 100 | U4: =IF(Q4<=0.25,100, IF(Q4<=0.35,80, IF(Q4<=0.5,60,30))) -> 100 | V4: =IF(D4>=10,100, IF(D4>=5,80, IF(D4>=2,60,30))) -> 100 | W4: =IF(M4=0,100,IF(M4=1,50,20)) -> 100 | X4: =IF(N4=0,100,IF(N4<=2,70,30)) -> 100 | Y4: =T4*0.35 + U4*0.25 + V4*0.15 + W4*0.15 + X4*0.1 -> 100 | Z4: =IF(Y4>=80,"Low Risk", IF(Y4>=65,"Medium Risk", IF(Y4>=50,"High Risk","Very High Risk"))) -> Low Risk | AA4: =IF(O4="Yes","Auto Decline", IF(M4>=2,"Auto Decline", IF(Q4>0.45,"High DTI Review", IF(S4>=2,"Enhanced Review","None")))) -> None | AB4: =IF(AA4="Auto Decline","Decline", IF(AA4="High DTI Review","Manual Review", IF(AA4="Enhanced Review","Manual Review", IF(Z4="Low Risk","Approve", IF(Z4="Medium Risk","Manual Review", IF(Z4="High Risk","Conditional Review","Decline")))))) -> Approve | AD4: Approved | AE4: =COUNTIF(AB2:AB21,"Approve") -> 14
A5: APP-004 | B5: 52 | C5: Self-Employed | D5: 20 | E5: 120000 | F5: 20000 | G5: 3500 | H5: 30000 | I5: 60 | J5: Auto | K5: 810 | L5: =IF(K5>=750,"Prime",IF(K5>=700,"Near-Prime","Subprime")) -> Prime | M5: 1 | N5: 3 | O5: No | P5: =E5/12 -> 10000 | Q5: =G5/P5 -> 0.35 | R5: =H5/E5 -> 0.25 | S5: =(M5>0)+(N5>=3)+(O5="Yes")+(Q5>0.4) -> 2 | T5: =IF(K5>=750,100, IF(K5>=700,85, IF(K5>=650,70, IF(K5>=600,50,30)))) -> 100 | U5: =IF(Q5<=0.25,100, IF(Q5<=0.35,80, IF(Q5<=0.5,60,30))) -> 80 | V5: =IF(D5>=10,100, IF(D5>=5,80, IF(D5>=2,60,30))) -> 100 | W5: =IF(M5=0,100,IF(M5=1,50,20)) -> 50 | X5: =IF(N5=0,100,IF(N5<=2,70,30)) -> 30 | Y5: =T5*0.35 + U5*0.25 + V5*0.15 + W5*0.15 + X5*0.1 -> 80.5 | Z5: =IF(Y5>=80,"Low Risk", IF(Y5>=65,"Medium Risk", IF(Y5>=50,"High Risk","Very High Risk"))) -> Low Risk | AA5: =IF(O5="Yes","Auto Decline", IF(M5>=2,"Auto Decline", IF(Q5>0.45,"High DTI Review", IF(S5>=2,"Enhanced Review","None")))) -> Enhanced Review | AB5: =IF(AA5="Auto Decline","Decline", IF(AA5="High DTI Review","Manual Review", IF(AA5="Enhanced Review","Manual Review", IF(Z5="Low Risk","Approve", IF(Z5="Medium Risk","Manual Review", IF(Z5="High Risk","Conditional Review","Decline")))))) -> Manual Review | AD5: Manual Review | AE5: =COUNTIF(AB2:AB21,"Manual Review") -> 5
A6: APP-005 | B6: 31 | C6: Salaried | D6: 5 | E6: 60000 | F6: 22000 | G6: 580 | H6: 18000 | I6: 36 | J6: Personal | K6: 650 | L6: =IF(K6>=750,"Prime",IF(K6>=700,"Near-Prime","Subprime")) -> Subprime | M6: 0 | N6: 1 | O6: No | P6: =E6/12 -> 5000 | Q6: =G6/P6 -> 0.116 | R6: =H6/E6 -> 0.3 | S6: =(M6>0)+(N6>=3)+(O6="Yes")+(Q6>0.4) -> 0 | T6: =IF(K6>=750,100, IF(K6>=700,85, IF(K6>=650,70, IF(K6>=600,50,30)))) -> 70 | U6: =IF(Q6<=0.25,100, IF(Q6<=0.35,80, IF(Q6<=0.5,60,30))) -> 100 | V6: =IF(D6>=10,100, IF(D6>=5,80, IF(D6>=2,60,30))) -> 80 | W6: =IF(M6=0,100,IF(M6=1,50,20)) -> 100 | X6: =IF(N6=0,100,IF(N6<=2,70,30)) -> 70 | Y6: =T6*0.35 + U6*0.25 + V6*0.15 + W6*0.15 + X6*0.1 -> 83.5 | Z6: =IF(Y6>=80,"Low Risk", IF(Y6>=65,"Medium Risk", IF(Y6>=50,"High Risk","Very High Risk"))) -> Low Risk | AA6: =IF(O6="Yes","Auto Decline", IF(M6>=2,"Auto Decline", IF(Q6>0.45,"High DTI Review", IF(S6>=2,"Enhanced Review","None")))) -> None | AB6: =IF(AA6="Auto Decline","Decline", IF(AA6="High DTI Review","Manual Review", IF(AA6="Enhanced Review","Manual Review", IF(Z6="Low Risk","Approve", IF(Z6="Medium Risk","Manual Review", IF(Z6="High Risk","Conditional Review","Decline")))))) -> Approve | AD6: Declined | AE6: =COUNTIF(AB2:AB21,"Decline") -> 1
A7: APP-006 | B7: 40 | C7: Salaried | D7: 10 | E7: 85000 | F7: 28000 | G7: 650 | H7: 22000 | I7: 60 | J7: Consolidation | K7: 700 | L7: =IF(K7>=750,"Prime",IF(K7>=700,"Near-Prime","Subprime")) -> Near-Prime | M7: 0 | N7: 2 | O7: No | P7: =E7/12 -> 7083.3333 | Q7: =G7/P7 -> 0.091764706 | R7: =H7/E7 -> 0.25882353 | S7: =(M7>0)+(N7>=3)+(O7="Yes")+(Q7>0.4) -> 0 | T7: =IF(K7>=750,100, IF(K7>=700,85, IF(K7>=650,70, IF(K7>=600,50,30)))) -> 85 | U7: =IF(Q7<=0.25,100, IF(Q7<=0.35,80, IF(Q7<=0.5,60,30))) -> 100 | V7: =IF(D7>=10,100, IF(D7>=5,80, IF(D7>=2,60,30))) -> 100 | W7: =IF(M7=0,100,IF(M7=1,50,20)) -> 100 | X7: =IF(N7=0,100,IF(N7<=2,70,30)) -> 70 | Y7: =T7*0.35 + U7*0.25 + V7*0.15 + W7*0.15 + X7*0.1 -> 91.75 | Z7: =IF(Y7>=80,"Low Risk", IF(Y7>=65,"Medium Risk", IF(Y7>=50,"High Risk","Very High Risk"))) -> Low Risk | AA7: =IF(O7="Yes","Auto Decline", IF(M7>=2,"Auto Decline", IF(Q7>0.45,"High DTI Review", IF(S7>=2,"Enhanced Review","None")))) -> None | AB7: =IF(AA7="Auto Decline","Decline", IF(AA7="High DTI Review","Manual Review", IF(AA7="Enhanced Review","Manual Review", IF(Z7="Low Risk","Approve", IF(Z7="Medium Risk","Manual Review", IF(Z7="High Risk","Conditional Review","Decline")))))) -> Approve | AD7: Approval Rate | AE7: =AE4/AE3 -> 0.7
A8: APP-007 | B8: 27 | C8: Contract | D8: 2 | E8: 48000 | F8: 15000 | G8: 1400 | H8: 12000 | I8: 36 | J8: Personal | K8: 610 | L8: =IF(K8>=750,"Prime",IF(K8>=700,"Near-Prime","Subprime")) -> Subprime | M8: 1 | N8: 4 | O8: No | P8: =E8/12 -> 4000 | Q8: =G8/P8 -> 0.35 | R8: =H8/E8 -> 0.25 | S8: =(M8>0)+(N8>=3)+(O8="Yes")+(Q8>0.4) -> 2 | T8: =IF(K8>=750,100, IF(K8>=700,85, IF(K8>=650,70, IF(K8>=600,50,30)))) -> 50 | U8: =IF(Q8<=0.25,100, IF(Q8<=0.35,80, IF(Q8<=0.5,60,30))) -> 80 | V8: =IF(D8>=10,100, IF(D8>=5,80, IF(D8>=2,60,30))) -> 60 | W8: =IF(M8=0,100,IF(M8=1,50,20)) -> 50 | X8: =IF(N8=0,100,IF(N8<=2,70,30)) -> 30 | Y8: =T8*0.35 + U8*0.25 + V8*0.15 + W8*0.15 + X8*0.1 -> 57 | Z8: =IF(Y8>=80,"Low Risk", IF(Y8>=65,"Medium Risk", IF(Y8>=50,"High Risk","Very High Risk"))) -> High Risk | AA8: =IF(O8="Yes","Auto Decline", IF(M8>=2,"Auto Decline", IF(Q8>0.45,"High DTI Review", IF(S8>=2,"Enhanced Review","None")))) -> Enhanced Review | AB8: =IF(AA8="Auto Decline","Decline", IF(AA8="High DTI Review","Manual Review", IF(AA8="Enhanced Review","Manual Review", IF(Z8="Low Risk","Approve", IF(Z8="Medium Risk","Manual Review", IF(Z8="High Risk","Conditional Review","Decline")))))) -> Manual Review | AD8: Avg Risk Score | AE8: =AVERAGE(Y2:Y21) -> 82.0875
A9: APP-008 | B9: 36 | C9: Salaried | D9: 7 | E9: 72000 | F9: 26000 | G9: 610 | H9: 20000 | I9: 60 | J9: Auto | K9: 690 | L9: =IF(K9>=750,"Prime",IF(K9>=700,"Near-Prime","Subprime")) -> Subprime | M9: 0 | N9: 1 | O9: No | P9: =E9/12 -> 6000 | Q9: =G9/P9 -> 0.10166667 | R9: =H9/E9 -> 0.27777778 | S9: =(M9>0)+(N9>=3)+(O9="Yes")+(Q9>0.4) -> 0 | T9: =IF(K9>=750,100, IF(K9>=700,85, IF(K9>=650,70, IF(K9>=600,50,30)))) -> 70 | U9: =IF(Q9<=0.25,100, IF(Q9<=0.35,80, IF(Q9<=0.5,60,30))) -> 100 | V9: =IF(D9>=10,100, IF(D9>=5,80, IF(D9>=2,60,30))) -> 80 | W9: =IF(M9=0,100,IF(M9=1,50,20)) -> 100 | X9: =IF(N9=0,100,IF(N9<=2,70,30)) -> 70 | Y9: =T9*0.35 + U9*0.25 + V9*0.15 + W9*0.15 + X9*0.1 -> 83.5 | Z9: =IF(Y9>=80,"Low Risk", IF(Y9>=65,"Medium Risk", IF(Y9>=50,"High Risk","Very High Risk"))) -> Low Risk | AA9: =IF(O9="Yes","Auto Decline", IF(M9>=2,"Auto Decline", IF(Q9>0.45,"High DTI Review", IF(S9>=2,"Enhanced Review","None")))) -> None | AB9: =IF(AA9="Auto Decline","Decline", IF(AA9="High DTI Review","Manual Review", IF(AA9="Enhanced Review","Manual Review", IF(Z9="Low Risk","Approve", IF(Z9="Medium Risk","Manual Review", IF(Z9="High Risk","Conditional Review","Decline")))))) -> Approve | AD9: % High / Very High Risk | AE9: =(COUNTIF(Z2:Z21,"High Risk")+COUNTIF(Z2:Z21,"Very High Risk"))/AE3 -> 0.15
A10: APP-009 | B10: 60 | C10: Salaried | D10: 25 | E10: 140000 | F10: 35000 | G10: 800 | H10: 35000 | I10: 60 | J10: Consolidation | K10: 790 | L10: =IF(K10>=750,"Prime",IF(K10>=700,"Near-Prime","Subprime")) -> Prime | M10: 0 | N10: 0 | O10: No | P10: =E10/12 -> 11666.667 | Q10: =G10/P10 -> 0.068571429 | R10: =H10/E10 -> 0.25 | S10: =(M10>0)+(N10>=3)+(O10="Yes")+(Q10>0.4) -> 0 | T10: =IF(K10>=750,100, IF(K10>=700,85, IF(K10>=650,70, IF(K10>=600,50,30)))) -> 100 | U10: =IF(Q10<=0.25,100, IF(Q10<=0.35,80, IF(Q10<=0.5,60,30))) -> 100 | V10: =IF(D10>=10,100, IF(D10>=5,80, IF(D10>=2,60,30))) -> 100 | W10: =IF(M10=0,100,IF(M10=1,50,20)) -> 100 | X10: =IF(N10=0,100,IF(N10<=2,70,30)) -> 100 | Y10: =T10*0.35 + U10*0.25 + V10*0.15 + W10*0.15 + X10*0.1 -> 100 | Z10: =IF(Y10>=80,"Low Risk", IF(Y10>=65,"Medium Risk", IF(Y10>=50,"High Risk","Very High Risk"))) -> Low Risk | AA10: =IF(O10="Yes","Auto Decline", IF(M10>=2,"Auto Decline", IF(Q10>0.45,"High DTI Review", IF(S10>=2,"Enhanced Review","None")))) -> None | AB10: =IF(AA10="Auto Decline","Decline", IF(AA10="High DTI Review","Manual Review", IF(AA10="Enhanced Review","Manual Review", IF(Z10="Low Risk","Approve", IF(Z10="Medium Risk","Manual Review", IF(Z10="High Risk","Conditional Review","Decline")))))) -> Approve
A11: APP-010 | B11: 49 | C11: Self-Employed | D11: 18 | E11: 98000 | F11: 24000 | G11: 1800 | H11: 24000 | I11: 36 | J11: Personal | K11: 670 | L11: =IF(K11>=750,"Prime",IF(K11>=700,"Near-Prime","Subprime")) -> Subprime | M11: 1 | N11: 2 | O11: No | P11: =E11/12 -> 8166.6667 | Q11: =G11/P11 -> 0.22040816 | R11: =H11/E11 -> 0.24489796 | S11: =(M11>0)+(N11>=3)+(O11="Yes")+(Q11>0.4) -> 1 | T11: =IF(K11>=750,100, IF(K11>=700,85, IF(K11>=650,70, IF(K11>=600,50,30)))) -> 70 | U11: =IF(Q11<=0.25,100, IF(Q11<=0.35,80, IF(Q11<=0.5,60,30))) -> 100 | V11: =IF(D11>=10,100, IF(D11>=5,80, IF(D11>=2,60,30))) -> 100 | W11: =IF(M11=0,100,IF(M11=1,50,20)) -> 50 | X11: =IF(N11=0,100,IF(N11<=2,70,30)) -> 70 | Y11: =T11*0.35 + U11*0.25 + V11*0.15 + W11*0.15 + X11*0.1 -> 79 | Z11: =IF(Y11>=80,"Low Risk", IF(Y11>=65,"Medium Risk", IF(Y11>=50,"High Risk","Very High Risk"))) -> Medium Risk | AA11: =IF(O11="Yes","Auto Decline", IF(M11>=2,"Auto Decline", IF(Q11>0.45,"High DTI Review", IF(S11>=2,"Enhanced Review","None")))) -> None | AB11: =IF(AA11="Auto Decline","Decline", IF(AA11="High DTI Review","Manual Review", IF(AA11="Enhanced Review","Manual Review", IF(Z11="Low Risk","Approve", IF(Z11="Medium Risk","Manual Review", IF(Z11="High Risk","Conditional Review","Decline")))))) -> Manual Review
A12: APP-011 | B12: 33 | C12: Salaried | D12: 4 | E12: 65000 | F12: 21000 | G12: 540 | H12: 17000 | I12: 36 | J12: Auto | K12: 640 | L12: =IF(K12>=750,"Prime",IF(K12>=700,"Near-Prime","Subprime")) -> Subprime | M12: 0 | N12: 1 | O12: No | P12: =E12/12 -> 5416.6667 | Q12: =G12/P12 -> 0.099692308 | R12: =H12/E12 -> 0.26153846 | S12: =(M12>0)+(N12>=3)+(O12="Yes")+(Q12>0.4) -> 0 | T12: =IF(K12>=750,100, IF(K12>=700,85, IF(K12>=650,70, IF(K12>=600,50,30)))) -> 50 | U12: =IF(Q12<=0.25,100, IF(Q12<=0.35,80, IF(Q12<=0.5,60,30))) -> 100 | V12: =IF(D12>=10,100, IF(D12>=5,80, IF(D12>=2,60,30))) -> 60 | W12: =IF(M12=0,100,IF(M12=1,50,20)) -> 100 | X12: =IF(N12=0,100,IF(N12<=2,70,30)) -> 70 | Y12: =T12*0.35 + U12*0.25 + V12*0.15 + W12*0.15 + X12*0.1 -> 73.5 | Z12: =IF(Y12>=80,"Low Risk", IF(Y12>=65,"Medium Risk", IF(Y12>=50,"High Risk","Very High Risk"))) -> Medium Risk | AA12: =IF(O12="Yes","Auto Decline", IF(M12>=2,"Auto Decline", IF(Q12>0.45,"High DTI Review", IF(S12>=2,"Enhanced Review","None")))) -> None | AB12: =IF(AA12="Auto Decline","Decline", IF(AA12="High DTI Review","Manual Review", IF(AA12="Enhanced Review","Manual Review", IF(Z12="Low Risk","Approve", IF(Z12="Medium Risk","Manual Review", IF(Z12="High Risk","Conditional Review","Decline")))))) -> Manual Review
A13: APP-012 | B13: 55 | C13: Self-Employed | D13: 22 | E13: 110000 | F13: 27000 | G13: 670 | H13: 28000 | I13: 60 | J13: Consolidation | K13: 750 | L13: =IF(K13>=750,"Prime",IF(K13>=700,"Near-Prime","Subprime")) -> Prime | M13: 0 | N13: 0 | O13: No | P13: =E13/12 -> 9166.6667 | Q13: =G13/P13 -> 0.073090909 | R13: =H13/E13 -> 0.25454545 | S13: =(M13>0)+(N13>=3)+(O13="Yes")+(Q13>0.4) -> 0 | T13: =IF(K13>=750,100, IF(K13>=700,85, IF(K13>=650,70, IF(K13>=600,50,30)))) -> 100 | U13: =IF(Q13<=0.25,100, IF(Q13<=0.35,80, IF(Q13<=0.5,60,30))) -> 100 | V13: =IF(D13>=10,100, IF(D13>=5,80, IF(D13>=2,60,30))) -> 100 | W13: =IF(M13=0,100,IF(M13=1,50,20)) -> 100 | X13: =IF(N13=0,100,IF(N13<=2,70,30)) -> 100 | Y13: =T13*0.35 + U13*0.25 + V13*0.15 + W13*0.15 + X13*0.1 -> 100 | Z13: =IF(Y13>=80,"Low Risk", IF(Y13>=65,"Medium Risk", IF(Y13>=50,"High Risk","Very High Risk"))) -> Low Risk | AA13: =IF(O13="Yes","Auto Decline", IF(M13>=2,"Auto Decline", IF(Q13>0.45,"High DTI Review", IF(S13>=2,"Enhanced Review","None")))) -> None | AB13: =IF(AA13="Auto Decline","Decline", IF(AA13="High DTI Review","Manual Review", IF(AA13="Enhanced Review","Manual Review", IF(Z13="Low Risk","Approve", IF(Z13="Medium Risk","Manual Review", IF(Z13="High Risk","Conditional Review","Decline")))))) -> Approve
A14: APP-013 | B14: 29 | C14: Contract | D14: 3 | E14: 56000 | F14: 16000 | G14: 2200 | H14: 13000 | I14: 36 | J14: Personal | K14: 600 | L14: =IF(K14>=750,"Prime",IF(K14>=700,"Near-Prime","Subprime")) -> Subprime | M14: 1 | N14: 3 | O14: No | P14: =E14/12 -> 4666.6667 | Q14: =G14/P14 -> 0.47142857 | R14: =H14/E14 -> 0.23214286 | S14: =(M14>0)+(N14>=3)+(O14="Yes")+(Q14>0.4) -> 3 | T14: =IF(K14>=750,100, IF(K14>=700,85, IF(K14>=650,70, IF(K14>=600,50,30)))) -> 50 | U14: =IF(Q14<=0.25,100, IF(Q14<=0.35,80, IF(Q14<=0.5,60,30))) -> 60 | V14: =IF(D14>=10,100, IF(D14>=5,80, IF(D14>=2,60,30))) -> 60 | W14: =IF(M14=0,100,IF(M14=1,50,20)) -> 50 | X14: =IF(N14=0,100,IF(N14<=2,70,30)) -> 30 | Y14: =T14*0.35 + U14*0.25 + V14*0.15 + W14*0.15 + X14*0.1 -> 52 | Z14: =IF(Y14>=80,"Low Risk", IF(Y14>=65,"Medium Risk", IF(Y14>=50,"High Risk","Very High Risk"))) -> High Risk | AA14: =IF(O14="Yes","Auto Decline", IF(M14>=2,"Auto Decline", IF(Q14>0.45,"High DTI Review", IF(S14>=2,"Enhanced Review","None")))) -> High DTI Review | AB14: =IF(AA14="Auto Decline","Decline", IF(AA14="High DTI Review","Manual Review", IF(AA14="Enhanced Review","Manual Review", IF(Z14="Low Risk","Approve", IF(Z14="Medium Risk","Manual Review", IF(Z14="High Risk","Conditional Review","Decline")))))) -> Manual Review
A15: APP-014 | B15: 42 | C15: Salaried | D15: 12 | E15: 90000 | F15: 29000 | G15: 690 | H15: 26000 | I15: 60 | J15: Auto | K15: 710 | L15: =IF(K15>=750,"Prime",IF(K15>=700,"Near-Prime","Subprime")) -> Near-Prime | M15: 0 | N15: 1 | O15: No | P15: =E15/12 -> 7500 | Q15: =G15/P15 -> 0.092 | R15: =H15/E15 -> 0.28888889 | S15: =(M15>0)+(N15>=3)+(O15="Yes")+(Q15>0.4) -> 0 | T15: =IF(K15>=750,100, IF(K15>=700,85, IF(K15>=650,70, IF(K15>=600,50,30)))) -> 85 | U15: =IF(Q15<=0.25,100, IF(Q15<=0.35,80, IF(Q15<=0.5,60,30))) -> 100 | V15: =IF(D15>=10,100, IF(D15>=5,80, IF(D15>=2,60,30))) -> 100 | W15: =IF(M15=0,100,IF(M15=1,50,20)) -> 100 | X15: =IF(N15=0,100,IF(N15<=2,70,30)) -> 70 | Y15: =T15*0.35 + U15*0.25 + V15*0.15 + W15*0.15 + X15*0.1 -> 91.75 | Z15: =IF(Y15>=80,"Low Risk", IF(Y15>=65,"Medium Risk", IF(Y15>=50,"High Risk","Very High Risk"))) -> Low Risk | AA15: =IF(O15="Yes","Auto Decline", IF(M15>=2,"Auto Decline", IF(Q15>0.45,"High DTI Review", IF(S15>=2,"Enhanced Review","None")))) -> None | AB15: =IF(AA15="Auto Decline","Decline", IF(AA15="High DTI Review","Manual Review", IF(AA15="Enhanced Review","Manual Review", IF(Z15="Low Risk","Approve", IF(Z15="Medium Risk","Manual Review", IF(Z15="High Risk","Conditional Review","Decline")))))) -> Approve
A16: APP-015 | B16: 38 | C16: Salaried | D16: 9 | E16: 78000 | F16: 26000 | G16: 630 | H16: 21000 | I16: 36 | J16: Personal | K16: 690 | L16: =IF(K16>=750,"Prime",IF(K16>=700,"Near-Prime","Subprime")) -> Subprime | M16: 0 | N16: 2 | O16: No | P16: =E16/12 -> 6500 | Q16: =G16/P16 -> 0.096923077 | R16: =H16/E16 -> 0.26923077 | S16: =(M16>0)+(N16>=3)+(O16="Yes")+(Q16>0.4) -> 0 | T16: =IF(K16>=750,100, IF(K16>=700,85, IF(K16>=650,70, IF(K16>=600,50,30)))) -> 70 | U16: =IF(Q16<=0.25,100, IF(Q16<=0.35,80, IF(Q16<=0.5,60,30))) -> 100 | V16: =IF(D16>=10,100, IF(D16>=5,80, IF(D16>=2,60,30))) -> 80 | W16: =IF(M16=0,100,IF(M16=1,50,20)) -> 100 | X16: =IF(N16=0,100,IF(N16<=2,70,30)) -> 70 | Y16: =T16*0.35 + U16*0.25 + V16*0.15 + W16*0.15 + X16*0.1 -> 83.5 | Z16: =IF(Y16>=80,"Low Risk", IF(Y16>=65,"Medium Risk", IF(Y16>=50,"High Risk","Very High Risk"))) -> Low Risk | AA16: =IF(O16="Yes","Auto Decline", IF(M16>=2,"Auto Decline", IF(Q16>0.45,"High DTI Review", IF(S16>=2,"Enhanced Review","None")))) -> None | AB16: =IF(AA16="Auto Decline","Decline", IF(AA16="High DTI Review","Manual Review", IF(AA16="Enhanced Review","Manual Review", IF(Z16="Low Risk","Approve", IF(Z16="Medium Risk","Manual Review", IF(Z16="High Risk","Conditional Review","Decline")))))) -> Approve
A17: APP-016 | B17: 47 | C17: Salaried | D17: 14 | E17: 102000 | F17: 31000 | G17: 2900 | H17: 29000 | I17: 60 | J17: Consolidation | K17: 730 | L17: =IF(K17>=750,"Prime",IF(K17>=700,"Near-Prime","Subprime")) -> Near-Prime | M17: 0 | N17: 0 | O17: No | P17: =E17/12 -> 8500 | Q17: =G17/P17 -> 0.34117647 | R17: =H17/E17 -> 0.28431373 | S17: =(M17>0)+(N17>=3)+(O17="Yes")+(Q17>0.4) -> 0 | T17: =IF(K17>=750,100, IF(K17>=700,85, IF(K17>=650,70, IF(K17>=600,50,30)))) -> 85 | U17: =IF(Q17<=0.25,100, IF(Q17<=0.35,80, IF(Q17<=0.5,60,30))) -> 80 | V17: =IF(D17>=10,100, IF(D17>=5,80, IF(D17>=2,60,30))) -> 100 | W17: =IF(M17=0,100,IF(M17=1,50,20)) -> 100 | X17: =IF(N17=0,100,IF(N17<=2,70,30)) -> 100 | Y17: =T17*0.35 + U17*0.25 + V17*0.15 + W17*0.15 + X17*0.1 -> 89.75 | Z17: =IF(Y17>=80,"Low Risk", IF(Y17>=65,"Medium Risk", IF(Y17>=50,"High Risk","Very High Risk"))) -> Low Risk | AA17: =IF(O17="Yes","Auto Decline", IF(M17>=2,"Auto Decline", IF(Q17>0.45,"High DTI Review", IF(S17>=2,"Enhanced Review","None")))) -> None | AB17: =IF(AA17="Auto Decline","Decline", IF(AA17="High DTI Review","Manual Review", IF(AA17="Enhanced Review","Manual Review", IF(Z17="Low Risk","Approve", IF(Z17="Medium Risk","Manual Review", IF(Z17="High Risk","Conditional Review","Decline")))))) -> Approve
A18: APP-017 | B18: 26 | C18: Contract | D18: 1 | E18: 45000 | F18: 14000 | G18: 1900 | H18: 10000 | I18: 36 | J18: Personal | K18: 580 | L18: =IF(K18>=750,"Prime",IF(K18>=700,"Near-Prime","Subprime")) -> Subprime | M18: 2 | N18: 5 | O18: Yes | P18: =E18/12 -> 3750 | Q18: =G18/P18 -> 0.50666667 | R18: =H18/E18 -> 0.22222222 | S18: =(M18>0)+(N18>=3)+(O18="Yes")+(Q18>0.4) -> 4 | T18: =IF(K18>=750,100, IF(K18>=700,85, IF(K18>=650,70, IF(K18>=600,50,30)))) -> 30 | U18: =IF(Q18<=0.25,100, IF(Q18<=0.35,80, IF(Q18<=0.5,60,30))) -> 30 | V18: =IF(D18>=10,100, IF(D18>=5,80, IF(D18>=2,60,30))) -> 30 | W18: =IF(M18=0,100,IF(M18=1,50,20)) -> 20 | X18: =IF(N18=0,100,IF(N18<=2,70,30)) -> 30 | Y18: =T18*0.35 + U18*0.25 + V18*0.15 + W18*0.15 + X18*0.1 -> 28.5 | Z18: =IF(Y18>=80,"Low Risk", IF(Y18>=65,"Medium Risk", IF(Y18>=50,"High Risk","Very High Risk"))) -> Very High Risk | AA18: =IF(O18="Yes","Auto Decline", IF(M18>=2,"Auto Decline", IF(Q18>0.45,"High DTI Review", IF(S18>=2,"Enhanced Review","None")))) -> Auto Decline | AB18: =IF(AA18="Auto Decline","Decline", IF(AA18="High DTI Review","Manual Review", IF(AA18="Enhanced Review","Manual Review", IF(Z18="Low Risk","Approve", IF(Z18="Medium Risk","Manual Review", IF(Z18="High Risk","Conditional Review","Decline")))))) -> Decline
A19: APP-018 | B19: 58 | C19: Self-Employed | D19: 30 | E19: 130000 | F19: 33000 | G19: 760 | H19: 33000 | I19: 60 | J19: Auto | K19: 800 | L19: =IF(K19>=750,"Prime",IF(K19>=700,"Near-Prime","Subprime")) -> Prime | M19: 0 | N19: 0 | O19: No | P19: =E19/12 -> 10833.333 | Q19: =G19/P19 -> 0.070153846 | R19: =H19/E19 -> 0.25384615 | S19: =(M19>0)+(N19>=3)+(O19="Yes")+(Q19>0.4) -> 0 | T19: =IF(K19>=750,100, IF(K19>=700,85, IF(K19>=650,70, IF(K19>=600,50,30)))) -> 100 | U19: =IF(Q19<=0.25,100, IF(Q19<=0.35,80, IF(Q19<=0.5,60,30))) -> 100 | V19: =IF(D19>=10,100, IF(D19>=5,80, IF(D19>=2,60,30))) -> 100 | W19: =IF(M19=0,100,IF(M19=1,50,20)) -> 100 | X19: =IF(N19=0,100,IF(N19<=2,70,30)) -> 100 | Y19: =T19*0.35 + U19*0.25 + V19*0.15 + W19*0.15 + X19*0.1 -> 100 | Z19: =IF(Y19>=80,"Low Risk", IF(Y19>=65,"Medium Risk", IF(Y19>=50,"High Risk","Very High Risk"))) -> Low Risk | AA19: =IF(O19="Yes","Auto Decline", IF(M19>=2,"Auto Decline", IF(Q19>0.45,"High DTI Review", IF(S19>=2,"Enhanced Review","None")))) -> None | AB19: =IF(AA19="Auto Decline","Decline", IF(AA19="High DTI Review","Manual Review", IF(AA19="Enhanced Review","Manual Review", IF(Z19="Low Risk","Approve", IF(Z19="Medium Risk","Manual Review", IF(Z19="High Risk","Conditional Review","Decline")))))) -> Approve
A20: APP-019 | B20: 35 | C20: Salaried | D20: 6 | E20: 70000 | F20: 25000 | G20: 600 | H20: 23000 | I20: 36 | J20: Consolidation | K20: 670 | L20: =IF(K20>=750,"Prime",IF(K20>=700,"Near-Prime","Subprime")) -> Subprime | M20: 0 | N20: 1 | O20: No | P20: =E20/12 -> 5833.3333 | Q20: =G20/P20 -> 0.10285714 | R20: =H20/E20 -> 0.32857143 | S20: =(M20>0)+(N20>=3)+(O20="Yes")+(Q20>0.4) -> 0 | T20: =IF(K20>=750,100, IF(K20>=700,85, IF(K20>=650,70, IF(K20>=600,50,30)))) -> 70 | U20: =IF(Q20<=0.25,100, IF(Q20<=0.35,80, IF(Q20<=0.5,60,30))) -> 100 | V20: =IF(D20>=10,100, IF(D20>=5,80, IF(D20>=2,60,30))) -> 80 | W20: =IF(M20=0,100,IF(M20=1,50,20)) -> 100 | X20: =IF(N20=0,100,IF(N20<=2,70,30)) -> 70 | Y20: =T20*0.35 + U20*0.25 + V20*0.15 + W20*0.15 + X20*0.1 -> 83.5 | Z20: =IF(Y20>=80,"Low Risk", IF(Y20>=65,"Medium Risk", IF(Y20>=50,"High Risk","Very High Risk"))) -> Low Risk | AA20: =IF(O20="Yes","Auto Decline", IF(M20>=2,"Auto Decline", IF(Q20>0.45,"High DTI Review", IF(S20>=2,"Enhanced Review","None")))) -> None | AB20: =IF(AA20="Auto Decline","Decline", IF(AA20="High DTI Review","Manual Review", IF(AA20="Enhanced Review","Manual Review", IF(Z20="Low Risk","Approve", IF(Z20="Medium Risk","Manual Review", IF(Z20="High Risk","Conditional Review","Decline")))))) -> Approve
A21: APP-020 | B21: 44 | C21: Salaried | D21: 16 | E21: 92000 | F21: 30000 | G21: 710 | H21: 27000 | I21: 60 | J21: Personal | K21: 740 | L21: =IF(K21>=750,"Prime",IF(K21>=700,"Near-Prime","Subprime")) -> Near-Prime | M21: 0 | N21: 0 | O21: No | P21: =E21/12 -> 7666.6667 | Q21: =G21/P21 -> 0.092608696 | R21: =H21/E21 -> 0.29347826 | S21: =(M21>0)+(N21>=3)+(O21="Yes")+(Q21>0.4) -> 0 | T21: =IF(K21>=750,100, IF(K21>=700,85, IF(K21>=650,70, IF(K21>=600,50,30)))) -> 85 | U21: =IF(Q21<=0.25,100, IF(Q21<=0.35,80, IF(Q21<=0.5,60,30))) -> 100 | V21: =IF(D21>=10,100, IF(D21>=5,80, IF(D21>=2,60,30))) -> 100 | W21: =IF(M21=0,100,IF(M21=1,50,20)) -> 100 | X21: =IF(N21=0,100,IF(N21<=2,70,30)) -> 100 | Y21: =T21*0.35 + U21*0.25 + V21*0.15 + W21*0.15 + X21*0.1 -> 94.75 | Z21: =IF(Y21>=80,"Low Risk", IF(Y21>=65,"Medium Risk", IF(Y21>=50,"High Risk","Very High Risk"))) -> Low Risk | AA21: =IF(O21="Yes","Auto Decline", IF(M21>=2,"Auto Decline", IF(Q21>0.45,"High DTI Review", IF(S21>=2,"Enhanced Review","None")))) -> None | AB21: =IF(AA21="Auto Decline","Decline", IF(AA21="High DTI Review","Manual Review", IF(AA21="Enhanced Review","Manual Review", IF(Z21="Low Risk","Approve", IF(Z21="Medium Risk","Manual Review", IF(Z21="High Risk","Conditional Review","Decline")))))) -> Approve
A25: Model Assumptions & Risk Flags
A27: Model Scope & Use
A28: This model is designed for initial credit risk screening and decision support. Final lending decisions may require manual review and additional underwriting checks.
A31: Key Assumptions
A32: (i) Income and debt values are assumed to be verified and accurate
A33: (ii) Credit score reflects most recent bureau pull
A34: (ii) Model weights reflect relative risk importance, not probability of default
A36: Credit Score Bands:
A37: Prime ≥ 750
A38: Near-Prime 700–749
A39: Subprime < 700
A41: Risk Flags Considered:
... A48: The model does not account for collateral value, interest rate, or macroeconomic conditions.

Sheet Risk_Model
A1: This sheet illustrates the credit risk scoring logic for a single applicant and is used for model explanation and validation. Final calculations have been done in the Cleaned_Data sheet.
A4: Factor | B4: Metric | C4: Score | D4: Weight | E4: Weighted_Score | G4: Credit Score Band | H4: Score
A5: Credit Score | B5: =Cleaned_Data!K2 -> 720 | C5: 85 | D5: 0.35 | E5: =C5*D5 -> 29.75 | G5: ≥750 | H5: 100
A6: Debt-to-Income | B6: =Cleaned_Data!Q2 -> 0.13384615 | C6: 100 | D6: 0.25 | E6: =C6*D6 -> 25 | G6: 700–749 | H6: 85
A7: Employment Stability | B7: =Cleaned_Data!D2 -> 3 | C7: 60 | D7: 0.15 | E7: =C7*D7 -> 9 | G7: 650–699 | H7: 70
A8: Past Defaults | B8: =Cleaned_Data!M2 -> 0 | C8: 100 | D8: 0.15 | E8: =C8*D8 -> 15 | G8: 600–649 | H8: 50
A9: Delinquencies | B9: =Cleaned_Data!N2 -> 1 | C9: 70 | D9: 0.1 | E9: =C9*D9 -> 7 | G9: <600 | H9: 30
E10: Total Risk Score
E11: =SUM(E5:E9) -> 85.75 | G11: DTI Range | H11: Score
G12: ≤20% | H12: 100
G13: 21–35% | H13: 80
G14: 36–50% | H14: 60
G15: >50% | H15: 30
G17: Employment Years | H17: Score
G18: ≥10 | H18: 100
G19: 5–9 | H19: 80
G20: 2–4 | H20: 60
G21: <2 | H21: 30
G23: Past Defaults | H23: Score
G24: 0 | H24: 100
G25: 1 | H25: 50
G26: ≥2 | H26: 20
G28: Delinquencies (12M) | H28: Score
G29: 0 | H29: 100
G30: 1–2 | H30: 70
G31: ≥3 | H31: 30

Sheet Risk_Model_Automated
A1: This sheet demonstrates automated model logic using a single-row input structure. Final calculations have been done in the Cleaned_Data sheet. A13 can be tested with any row number taken from the Cleaned_Data sheet.
A5: Factor | B5: Metric | C5: Score | D5: Weight | E5: Weighted_Score | G5: Credit Score Band | H5: Score
A6: Credit Score | B6: {=INDEX(Cleaned_Data!K:K,$B$14)} -> 720 | C6: =IF(B6>=750,100,IF(B6>=700,85,IF(B6>=650,70,IF(B6>=600,50,30)))) -> 85 | D6: 0.35 | E6: =C6*D6 -> 29.75 | G6: ≥750 | H6: 100
A7: Debt-to-Income | B7: {=INDEX(Cleaned_Data!Q:Q,$B$14)} -> 0.13384615 | C7: =IF(B7<=0.2,100,IF(B7<=0.35,80,IF(B7<=0.5,60,30))) -> 100 | D7: 0.25 | E7: =C7*D7 -> 25 | G7: 700–749 | H7: 85
A8: Employment Stability | B8: {=INDEX(Cleaned_Data!D:D,$B$14)} -> 3 | C8: =IF(B8>=10,100,IF(B8>=5,80,IF(B8>=2,60,30))) -> 60 | D8: 0.15 | E8: =C8*D8 -> 9 | G8: 650–699 | H8: 70
A9: Past Defaults | B9: {=INDEX(Cleaned_Data!M:M,$B$14)} -> 0 | C9: =IF(B9=0,100,IF(B9=1,50,20)) -> 100 | D9: 0.15 | E9: =C9*D9 -> 15 | G9: 600–649 | H9: 50
A10: Delinquencies | B10: {=INDEX(Cleaned_Data!N:N,$B$14)} -> 1 | C10: =IF(B10=0,100,IF(B10<=2,70,30)) -> 70 | D10: 0.1 | E10: =C10*D10 -> 7 | G10: <600 | H10: 30
E11: Total Risk Score
E12: =SUM(E6:E10) -> 85.75 | G12: DTI Range | H12: Score
G13: ≤20% | H13: 100
A14: Active_Data_Row | B14: 2 | D14: Risk Tier | E14: =IF(E12>=80,"Low Risk",IF(E12>=65,"Medium Risk",IF(E12>=50,"High Risk","Very High Risk"))) -> Low Risk | G14: 21–35% | H14: 80
D15: Lending Decision | E15: =IF(E14="Low Risk","Approve",IF(E14="Medium Risk","Manual Review",IF(E14="High Risk","Conditional Review","Decline"))) -> Approve | G15: 36–50% | H15: 60
G16: >50% | H16: 30
G18: Employment Years | H18: Score
G19: ≥10 | H19: 100
G20: 5–9 | H20: 80
G21: 2–4 | H21: 60
G22: <2 | H22: 30
G24: Past Defaults | H24: Score
G25: 0 | H25: 100
G26: 1 | H26: 50
G27: ≥2 | H27: 20
G29: Delinquencies (12M) | H29: Score
G30: 0 | H30: 100
G31: 1–2 | H31: 70
G32: ≥3 | H32: 30
