Workbook

Sheet GL_Raw
A1: Date | B1: Account | C1: Account Type | D1: Department | E1: Debit | F1: Credit
A2: 45717 | B2: Subscription Revenue | C2: Revenue | D2: Sales | F2: 4200000
A3: 45717 | B3: Accounts Receivable | C3: Asset | D3: Finance | E3: 4200000
A4: 45718 | B4: Content Licensing Costs | C4: Expense | D4: Content | E4: 1100000
A5: 45718 | B5: Accounts Payable | C5: Liability | D5: Finance | F5: 1100000
A6: 45721 | B6: Payroll Expense | C6: Expense | D6: HR | E6: 420000
A7: 45721 | B7: Cash | C7: Asset | D7: Finance | F7: 420000
A8: 45722 | B8: Marketing Expense | C8: Expense | D8: Marketing | E8: 350000
A9: 45722 | B9: Accounts Payable | C9: Liability | D9: Finance | F9: 350000
A10: 45724 | B10: Cloud Infrastructure Expense | C10: Expense | D10: Technology | E10: 275000
A11: 45724 | B11: Accounts Payable | C11: Liability | D11: Finance | F11: 275000
A12: 45726 | B12: Cash | C12: Asset | D12: Finance | E12: 2000000
A13: 45726 | B13: Accounts Receivable | C13: Asset | D13: Finance | F13: 2000000
A14: 45728 | B14: Office & G&A Expense | C14: Expense | D14: Admin | E14: 125000
A15: 45728 | B15: Accounts Payable | C15: Liability | D15: Finance | F15: 125000
A16: 45731 | B16: Accrued Content Expense | C16: Expense | D16: Content | E16: 220000
A17: 45731 | B17: Accrued Expenses | C17: Liability | D17: Finance | F17: 220000
A18: 45736 | B18: Accounts Payable | C18: Liability | D18: Finance | E18: 200000
A19: 45736 | B19: Cash | C19: Asset | D19: Finance | F19: 200000
A20: 45741 | B20: Accrued Expenses | C20: Liability | D20: Finance | E20: 100000
A21: 45741 | B21: Cash | C21: Asset | D21: Finance | F21: 100000

Sheet Trial_Balance
A1: Row Labels | B1: Total Debit | C1: Total Credit | D1: Net Balance | E1: Financial Statement
A2: Accounts Payable | B2: 200000 | C2: 1850000 | D2: =B2-C2 -> -1650000 | E2: Balance Sheet
A3: Accounts Receivable | B3: 4200000 | C3: 2000000 | D3: =B3-C3 -> 2200000 | E3: Balance Sheet
A4: Accrued Content Expense | B4: 220000 | D4: =B4-C4 -> 220000 | E4: Income Statement
A5: Accrued Expenses | B5: 100000 | C5: 220000 | D5: =B5-C5 -> -120000 | E5: Balance Sheet
A6: Cash | B6: 2000000 | C6: 720000 | D6: =B6-C6 -> 1280000 | E6: Balance Sheet
A7: Cloud Infrastructure Expense | B7: 275000 | D7: =B7-C7 -> 275000 | E7: Income Statement
A8: Content Licensing Costs | B8: 1100000 | D8: =B8-C8 -> 1100000 | E8: Income Statement
A9: Marketing Expense | B9: 350000 | D9: =B9-C9 -> 350000 | E9: Income Statement
A10: Office & G&A Expense | B10: 125000 | D10: =B10-C10 -> 125000 | E10: Income Statement
A11: Payroll Expense | B11: 420000 | D11: =B11-C11 -> 420000 | E11: Income Statement
A12: Subscription Revenue | C12: 4200000 | D12: =B12-C12 -> -4200000 | E12: Income Statement
A13: Grand Total | B13: 8990000 | C13: 8990000 | D13: =SUM(D2:D12) -> 0

Sheet Income_Statement
A1: Income Statement
A2: For the Month Ended March 31, 2025
A4: Account | B4: Amount
A5: Revenue
A6: Subscription Revenue | B6: =SUMIFS(Trial_Balance!$D:$D, Trial_Balance!$A:$A, A6) -> -4200000
A7: Total Revenue | B7: =B6 -> -4200000
A9: Operating Expenses
A10: Content Licensing Costs | B10: =SUMIFS(Trial_Balance!$D:$D, Trial_Balance!$A:$A, A10) -> 1100000
A11: Accrued Content Expense | B11: =SUMIFS(Trial_Balance!$D:$D, Trial_Balance!$A:$A, A11) -> 220000
A12: Cloud Infrastructure Expense | B12: =SUMIFS(Trial_Balance!$D:$D, Trial_Balance!$A:$A, A12) -> 275000
A13: Marketing Expense | B13: =SUMIFS(Trial_Balance!$D:$D, Trial_Balance!$A:$A, A13) -> 350000
A14: Payroll Expense | B14: =SUMIFS(Trial_Balance!$D:$D, Trial_Balance!$A:$A, A14) -> 420000
A15: Office & G&A Expense | B15: =SUMIFS(Trial_Balance!$D:$D, Trial_Balance!$A:$A, A15) -> 125000
A16: Total Operating Expenses | B16: =SUM(B10:B15) -> 2490000
A18: Operating Income | B18: =B7+B16 -> -1710000
A21: Note:
A22: Credits are displayed as negative and debits are displayed as positive. This does not reflect the gain or loss.

Sheet Balance_Sheet
A1: Balance Sheet
A2: As of March 31, 2025
A4: Account | B4: Amount
A5: Assets
A6: Cash | B6: =SUMIFS(Trial_Balance!$D:$D, Trial_Balance!$A:$A, A6) -> 1280000
A7: Accounts Receivable | B7: =SUMIFS(Trial_Balance!$D:$D, Trial_Balance!$A:$A, A7) -> 2200000
A8: Total Assets | B8: =SUM(B6:B7) -> 3480000
A10: Liabilities
A11: Accounts Payable | B11: =-SUMIFS(Trial_Balance!$D:$D, Trial_Balance!$A:$A, A11) -> 1650000
A12: Accrued Expenses | B12: =-SUMIFS(Trial_Balance!$D:$D, Trial_Balance!$A:$A, A12) -> 120000
A13: Total Liabilities | B13: =SUM(B11:B12) -> 1770000
A15: Equity
A16: Retained Earnings | B16: =-Income_Statement!B18 -> 1710000
A17: Total Liabilities and Equity | B17: =B13+B16 -> 3480000

Sheet Ratios_Analysis
A1: Key Financial Ratios
A3: Ratio | B3: Formula | C3: Value | D3: Note
A4: Gross Margin % | B4: Gross Profit / Revenue | C4: =(ABS(Income_Statement!B7)-Income_Statement!B10)/ABS(Income_Statement!B7) -> 0.73809524 | D4: Content Licensing Costs is the primary cost of revenue
A5: Operating Margin % | B5: Operating Income / Revenue | C5: =ABS(Income_Statement!B18)/ABS(Income_Statement!B7) -> 0.40714286
A6: Current Ratio | B6: Current Assets / Current Liabilities | C6: =Balance_Sheet!B8/Balance_Sheet!B13 -> 1.9661017
A7: Payroll Expense Ratio % | B7: Payroll Expense / Revenue | C7: =Income_Statement!B14/ABS(Income_Statement!B7) -> 0.1
A8: Content Cost Ratio % | B8: Content Costs / Revenue | C8: =(Income_Statement!B10+Income_Statement!B11)/ABS(Income_Statement!B7) -> 0.31428571 | D8: Content Costs = Content Licensing Costs + Accrued Content Costs
