Workbook

Sheet Raw_Data
B1: 2023 | C1: 2024 | D1: 2025
A2: Product Revenue | B2: 298085 | C2: 294866 | D2: 307003
A3: Services Revenue | B3: 85200 | C3: 96169 | D3: 109158
A4: Total Revenue | B4: 383285 | C4: 391035 | D4: 416161
A5: Total Cost of Sales | B5: 214137 | C5: 210352 | D5: 220960
A6: Gross Margin | B6: 169148 | C6: 180683 | D6: 195201
A7: R&D Expense | B7: 29915 | C7: 31370 | D7: 34550
A8: SG&A Expense | B8: 24932 | C8: 26097 | D8: 27601
A9: Total Operating Expenses | B9: 54847 | C9: 57467 | D9: 62151
A10: Operating Income | B10: 114301 | C10: 123216 | D10: 133050
A11: Net Income | B11: 96995 | C11: 93736 | D11: 112010
A13: Source: Apple Inc. Form 10-K filings (FY23 – FY25)

Sheet Clean_Data
B1: 2023 | C1: 2024 | D1: 2025 | E1: YoY % (24 vs 23) | F1: YoY % (25 vs 24)
A2: Revenue - Total | B2: =Raw_Data!B4 -> 383285 | C2: =Raw_Data!C4 -> 391035 | D2: =Raw_Data!D4 -> 416161 | E2: =(C2/B2)-1 -> 0.020219941 | F2: =(D2/C2)-1 -> 0.064255118
A3: Revenue - Products | B3: =Raw_Data!B2 -> 298085 | C3: =Raw_Data!C2 -> 294866 | D3: =Raw_Data!D2 -> 307003 | E3: =(C3/B3)-1 -> -0.010798933 | F3: =(D3/C3)-1 -> 0.04116107
A4: Revenue - Services | B4: =Raw_Data!B3 -> 85200 | C4: =Raw_Data!C3 -> 96169 | D4: =Raw_Data!D3 -> 109158 | E4: =(C4/B4)-1 -> 0.12874413 | F4: =(D4/C4)-1 -> 0.13506431
A5: Gross Margin | B5: =Raw_Data!B6 -> 169148 | C5: =Raw_Data!C6 -> 180683 | D5: =Raw_Data!D6 -> 195201 | E5: =(C5/B5)-1 -> 0.068194717 | F5: =(D5/C5)-1 -> 0.080350669
A6: Gross Margin % | B6: =B5/B2 -> 0.4413113 | C6: =C5/C2 -> 0.4620635 | D6: =D5/D2 -> 0.46905164 | E6: =(C6/B6)-1 -> 0.047023955 | F6: =(D6/C6)-1 -> 0.015123772
A7: Operating Expenses | B7: =Raw_Data!B9 -> 54847 | C7: =Raw_Data!C9 -> 57467 | D7: =Raw_Data!D9 -> 62151 | E7: =(C7/B7)-1 -> 0.047769249 | F7: =(D7/C7)-1 -> 0.081507648
A8: Operating Income | B8: =Raw_Data!B10 -> 114301 | C8: =Raw_Data!C10 -> 123216 | D8: =Raw_Data!D10 -> 133050 | E8: =(C8/B8)-1 -> 0.077995818 | F8: =(D8/C8)-1 -> 0.079811063
A9: Operating Margin % | B9: =B8/B2 -> 0.29821412 | C9: =C8/C2 -> 0.31510223 | D9: =D8/D2 -> 0.319708 | E9: =(C9/B9)-1 -> 0.056630806 | F9: =(D9/C9)-1 -> 0.014616745
A10: Net Income | B10: =Raw_Data!B11 -> 96995 | C10: =Raw_Data!C11 -> 93736 | D10: =Raw_Data!D11 -> 112010
A11: Net Margin % | B11: =B10/B2 -> 0.25306234 | C11: =C10/C2 -> 0.23971256 | D11: =D10/D2 -> 0.26915064

Sheet Analysis_Model
A2: Year | B2: Total Revenue ($M)
A3: FY23 | B3: =Clean_Data!B2 -> 383285
A4: FY24 | B4: =Clean_Data!C2 -> 391035
A5: FY25 | B5: =Clean_Data!D2 -> 416161
A8: Year | B8: Product Revenue ($M) | C8: Services Revenue ($M)
A9: FY23 | B9: =Clean_Data!B3 -> 298085 | C9: =Clean_Data!B4 -> 85200
A10: FY24 | B10: =Clean_Data!C3 -> 294866 | C10: =Clean_Data!C4 -> 96169
A11: FY25 | B11: =Clean_Data!D3 -> 307003 | C11: =Clean_Data!D4 -> 109158
A14: Year | B14: Operating Margin %
A15: FY23 | B15: =Clean_Data!B9 -> 0.29821412
A16: FY24 | B16: =Clean_Data!C9 -> 0.31510223
A17: FY25 | B17: =Clean_Data!D9 -> 0.319708
A20: FY26 Forecast Assumptions
A21: Assumption | B21: Base Case | C21: Upside Case | D21: Downside Case
A22: Product Revenue Growth | B22: 0.01 | C22: 0.03 | D22: -0.02
A23: Services Revenue Growth | B23: 0.08 | C23: 0.12 | D23: 0.05
A26: FY26 Revenue Forecast ($M)
A27: Item | B27: Base | C27: Upside | D27: Downside
A28: FY25 Product Revenue | B28: =Clean_Data!D3 -> 307003 | C28: =Clean_Data!D3 -> 307003 | D28: =Clean_Data!D3 -> 307003
A29: FY25 Services Revenue | B29: =Clean_Data!D4 -> 109158 | C29: =Clean_Data!D4 -> 109158 | D29: =Clean_Data!D4 -> 109158
A30: Product Growth Assumption | B30: =B22 -> 0.01 | C30: =C22 -> 0.03 | D30: =D22 -> -0.02
A31: Services Growth Assumption | B31: =B23 -> 0.08 | C31: =C23 -> 0.12 | D31: =D23 -> 0.05
A32: FY26 Product Revenue | B32: =B28 * (1 + B30) -> 310073.03 | C32: =C28 * (1 + C30) -> 316213.09 | D32: =D28 * (1 + D30) -> 300862.94
A33: FY26 Services Revenue | B33: =B29 * (1 + B31) -> 117890.64 | C33: =C29 * (1 + C31) -> 122256.96 | D33: =D29 * (1 + D31) -> 114615.9
A34: Total FY26 Revenue | B34: =SUM(B32:B33) -> 427963.67 | C34: =SUM(C32:C33) -> 438470.05 | D34: =SUM(D32:D33) -> 415478.84
A37: Scenario | B37: FY26 Total Revenue ($M)
A38: Downside | B38: =D34 -> 415478.84
A39: Base | B39: =B34 -> 427963.67
A40: Upside | B40: =C34 -> 438470.05

Sheet Dashboard
B3: =Clean_Data!D2 -> 416161 | E3: =Clean_Data!F2 -> 0.064255118 | H3: =Clean_Data!D9 -> 0.319708 | K3: =Clean_Data!D11 -> 0.26915064
